concurrent_openai/__init__.py
concurrent_openai/client.py
concurrent_openai/models.py
concurrent_openai/rate_limiter.py
concurrent_openai/utils.py
concurrent_openai-1.2.2.dist-info/LICENSE
concurrent_openai-1.2.2.dist-info/METADATA
concurrent_openai-1.2.2.dist-info/WHEEL
concurrent_openai-1.2.2.dist-info/RECORD
