Metadata-Version: 2.3
Name: concurrent-openai
Version: 1.2.2
Summary: Python library for asynchronous interactions with the OpenAI API, enabling concurrent request handling. It simplifies building scalable, AI-powered applications by offering efficient, rate-limited access to OpenAI services. Perfect for developers seeking to integrate OpenAI's capabilities with minimal overhead.
License: MIT
Author: Stefanescu Marian
Author-email: marianstefi20@gmail.com
Requires-Python: >=3.11,<4.0
Classifier: License :: OSI Approved :: MIT License
Classifier: Programming Language :: Python :: 3
Classifier: Programming Language :: Python :: 3.11
Classifier: Programming Language :: Python :: 3.12
Classifier: Programming Language :: Python :: 3.13
Requires-Dist: openai (>=1.61.0,<2.0.0)
Requires-Dist: python-dotenv (>=1.0.1,<2.0.0)
Requires-Dist: structlog (>=24.1.0,<25.0.0)
Requires-Dist: tiktoken (>=0.7.0,<0.8.0)
Project-URL: Repository, https://github.com/marianstefi20/concurrent-openai
